rec2slide/__init__.py
rec2slide/example.py
rec2slide/model.py
rec2slide/rec2slide.py
rec2slide/scorer.py
rec2slide/utils.py
rec2slide-0.1.2.dist-info/METADATA
rec2slide-0.1.2.dist-info/WHEEL
rec2slide-0.1.2.dist-info/RECORD
